INSTALL
MANIFEST.in
README
README.md
RELEASE-1.1.0
apacheLICENSE-2.0.txt
gpl-3.0.txt
license.txt
python_path.txt
release.py
scriptutils.py
setup.py
contrib/archlinux/.gitignore
contrib/archlinux/PKGBUILD
contrib/gentoo/README
contrib/gentoo/lpod-python-0.9.0.ebuild
contrib/gentoo/lpod-python-0.9.1.ebuild
contrib/gentoo/lpod-python-0.9.2.ebuild
doc_make/.DS_Store
doc_make/Makefile
doc_make/autodocs.rst
doc_make/conf.py
doc_make/index.rst
doc_make/sphinx-link.py
doc_make/static_in/LinLibertine_R.woff
doc_make/static_in/README
doc_make/static_in/banner-lpod_en.png
doc_make/static_in/lpod.css
documentation/.DS_Store
documentation/former_releases_notices/RELEASE-0.8
documentation/former_releases_notices/RELEASE-0.9.0
documentation/former_releases_notices/RELEASE-0.9.1
documentation/former_releases_notices/RELEASE-0.9.2
documentation/former_releases_notices/RELEASE-0.9.3
documentation/html/.buildinfo
documentation/html/autodocs.html
documentation/html/genindex.html
documentation/html/index.html
documentation/html/objects.inv
documentation/html/py-modindex.html
documentation/html/search.html
documentation/html/searchindex.js
documentation/html/_sources/autodocs.txt
documentation/html/_sources/index.txt
documentation/html/_sources/autodocs/_flags.txt
documentation/html/_sources/autodocs/_version.txt
documentation/html/_sources/autodocs/bookmark.txt
documentation/html/_sources/autodocs/cleaner.txt
documentation/html/_sources/autodocs/const.txt
documentation/html/_sources/autodocs/container.txt
documentation/html/_sources/autodocs/content.txt
documentation/html/_sources/autodocs/datatype.txt
documentation/html/_sources/autodocs/document.txt
documentation/html/_sources/autodocs/draw_page.txt
documentation/html/_sources/autodocs/element.txt
documentation/html/_sources/autodocs/experimental.txt
documentation/html/_sources/autodocs/frame.txt
documentation/html/_sources/autodocs/future.txt
documentation/html/_sources/autodocs/heading.txt
lpod_python.egg-info/PKG-INFO
lpod_python.egg-info/SOURCES.txt
lpod_python.egg-info/dependency_links.txt
lpod_python.egg-info/top_level.txt
