Metadata-Version: 1.0
Name: lpod-python
Version: 1.1.6
Summary: lpOD Library
Home-page: http://www.lpod-project.net/
Author: lpOD Team
Author-email: team@lpod-project.net
License: GPLv3 + Apache v2
Platform: UNKNOWN
